anna_agent/__init__.py
anna_agent/__main__.py
anna_agent/anna_agent_template.py
anna_agent/backbone.py
anna_agent/cli.py
anna_agent/common/registry.py
anna_agent/complaint_chain.py
anna_agent/complaint_elicitor.py
anna_agent/config/__init__.py
anna_agent/config/defaults.py
anna_agent/config/environment_reader.py
anna_agent/config/init_content.py
anna_agent/config/initialize.py
anna_agent/config/load_config.py
anna_agent/config/models/anna_engine_config.py
anna_agent/counselor.py
anna_agent/datasets/cbt-triggering-events.csv
anna_agent/emotion_modulator.py
anna_agent/emotion_pertuber.py
anna_agent/event_trigger.py
anna_agent/figure/readme.md
anna_agent/figure/whiteboard_exported_image_en.png
anna_agent/fill_scales.py
anna_agent/initialize.py
anna_agent/ms_patient.py
anna_agent/querier.py
anna_agent/scales/__init__.py
anna_agent/scales/bdi.json
anna_agent/scales/ghq-28.json
anna_agent/scales/sass.json
anna_agent/server/complaint.sh
anna_agent/server/counselor.sh
anna_agent/server/emotion.sh
anna_agent/short_term_memory.py
anna_agent/style_analyzer.py
anna_agent-0.1.1.dist-info/LICENSE
anna_agent-0.1.1.dist-info/METADATA
anna_agent-0.1.1.dist-info/WHEEL
anna_agent-0.1.1.dist-info/entry_points.txt
anna_agent-0.1.1.dist-info/RECORD
