Metadata-Version: 2.1
Name: anna_agent
Version: 0.1.1
Summary: Dynamic Evolution Agent System with Multi-Session Memory for Realistic Seeker Simulation
Requires-Python: >=3.10,<4.0
Classifier: Programming Language :: Python :: 3
Classifier: Programming Language :: Python :: 3.10
Classifier: Programming Language :: Python :: 3.11
Classifier: Programming Language :: Python :: 3.12
Classifier: Programming Language :: Python :: 3.13
Requires-Dist: PyYAML
Requires-Dist: environs
Requires-Dist: openai
Requires-Dist: pandas
Requires-Dist: pydantic
Requires-Dist: python-dotenv
Requires-Dist: typer[all]
